{
  "parent": "minecraft:recipes/root",
  "criteria": {
    "has_abyss_shard": {
      "conditions": {
        "items": [
          {
            "items": "warlocksmod:abyss_shard"
          }
        ]
      },
      "trigger": "minecraft:inventory_changed"
    },
    "has_the_recipe": {
      "conditions": {
        "recipe": "warlocksmod:abyss_shard_helmet"
      },
      "trigger": "minecraft:recipe_unlocked"
    }
  },
  "requirements": [
    [
      "has_the_recipe",
      "has_abyss_shard"
    ]
  ],
  "rewards": {
    "recipes": [
      "warlocksmod:abyss_shard_helmet"
    ]
  }
}